starlings/config.py
starlings/starlings.cpython-312-darwin.so
starlings/expressions.py
starlings/__init__.py
starlings/generators.py
starlings/debug.py
starlings/metrics/__init__.py
starlings/metrics/stats.py
starlings/metrics/eval.py
starlings-0.2.3.dist-info/RECORD
starlings-0.2.3.dist-info/WHEEL
starlings-0.2.3.dist-info/METADATA
starlings-0.2.3.dist-info/licenses/LICENSE
