Metadata-Version: 2.4
Name: starlings
Version: 0.2.3
Classifier: Development Status :: 3 - Alpha
Classifier: Intended Audience :: Developers
Classifier: License :: OSI Approved :: MIT License
Classifier: Programming Language :: Python :: 3
Classifier: Programming Language :: Python :: 3.10
Classifier: Programming Language :: Python :: 3.11
Classifier: Programming Language :: Python :: 3.12
Classifier: Programming Language :: Python :: 3.13
Classifier: Programming Language :: Python :: 3.14
Classifier: Programming Language :: Rust
Requires-Dist: numpy>=2.2.6
Requires-Dist: tqdm>=4.66.0
Requires-Dist: psutil>=5.9.0
License-File: LICENSE
Summary: A Python package for comparing entity resolutions from different processes
Keywords: entity-resolution,data-processing,rust
Author: Will Langdale
Requires-Python: >=3.10
